hissp/__init__.py
hissp/__main__.py
hissp/compiler.py
hissp/macros.lissp
hissp/macros.py
hissp/munger.py
hissp/reader.py
hissp/repl.py
hissp-0.5.0.dist-info/LICENSE.txt
hissp-0.5.0.dist-info/METADATA
hissp-0.5.0.dist-info/WHEEL
hissp-0.5.0.dist-info/entry_points.txt
hissp-0.5.0.dist-info/top_level.txt
hissp-0.5.0.dist-info/RECORD
