Metadata-Version: 2.1
Name: hissp
Version: 0.5.0
Summary: It's Python with a Lissp.
Home-page: https://github.com/gilch/hissp
Author: Matthew Egan Odendahl
Author-email: gilch@users.noreply.github.com
License: Apache-2.0
Keywords: lisp macro metaprogramming compiler interpreter DSL AST transpiler emacs clojure scheme language minimal REPL metaprogramming macros extensible s-expressions code-generation no-dependencies quasiquote backquote syntax-quote template Hissp Lissp destructuring
Classifier: Development Status :: 4 - Beta
Classifier: Environment :: Console
Classifier: Intended Audience :: Developers
Classifier: License :: OSI Approved :: Apache Software License
Classifier: Natural Language :: English
Classifier: Operating System :: MacOS :: MacOS X
Classifier: Operating System :: Microsoft :: Windows
Classifier: Operating System :: POSIX
Classifier: Operating System :: Unix
Classifier: Programming Language :: Python :: 3
Classifier: Programming Language :: Python :: 3.10
Classifier: Programming Language :: Lisp
Classifier: Topic :: Software Development
Classifier: Topic :: Software Development :: Code Generators
Classifier: Topic :: Software Development :: Compilers
Classifier: Topic :: Software Development :: Interpreters
Classifier: Topic :: Software Development :: Libraries
Classifier: Topic :: Software Development :: Libraries :: Python Modules
Classifier: Topic :: Software Development :: Pre-processors
Requires-Python: >=3.10
License-File: LICENSE.txt
